PneumoCVUTFBMI/DeviceLoader.py
PneumoCVUTFBMI/__init__.py
PneumoCVUTFBMI/main.py
pneumocvutfbmi-0.1.0.dist-info/METADATA
pneumocvutfbmi-0.1.0.dist-info/WHEEL
pneumocvutfbmi-0.1.0.dist-info/licenses/LICENSE
pneumocvutfbmi-0.1.0.dist-info/RECORD
