Metadata-Version: 2.1
Name: PneumoCVUTFBMI
Version: 0.1.0
Summary: Small library to communicate with pneumatic device created for CVUT FBMI
Author-email: Aleksei Karavaev <alexok997@gmail.com>
License-File: LICENSE
Classifier: License :: OSI Approved :: MIT License
Classifier: Operating System :: OS Independent
Classifier: Programming Language :: Python :: 3
Requires-Python: >=3.7
Requires-Dist: numpy
Requires-Dist: pymodbus>=2.9
Requires-Dist: pyserial
Requires-Dist: simpleloggerv1>=0.2.1
Requires-Dist: simplestepperdriverv1>=0.1.1
